{
  "team_id": "barcelona",
  "players": [
    {
      "id": "yamal",
      "name": "Ламин Ямал",
      "name_en": "Lamine Yamal",
      "age": 17,
      "nationality": "spain",
      "position": "rw",
      "secondary_positions": ["lw"],
      "foot": "left",
      "height": 180,
      "weight": 68,
      "rating": 86,
      "potential": 96,
      "stats": {
        "pace": 88,
        "shooting": 80,
        "passing": 82,
        "dribbling": 90,
        "defending": 30,
        "physical": 55,
        "finishing": 80,
        "heading": 42,
        "long_shots": 78,
        "composure": 85,
        "positioning": 80,
        "stamina": 78,
        "strength": 50,
        "jumping": 42,
        "agility": 92
      },
      "hidden_stats": {
        "injury_proneness": 25,
        "big_match_performance": 85,
        "consistency": 82,
        "adaptability": 80,
        "ambition": 95,
        "loyalty": 90,
        "pressure": 85,
        "professionalism": 85
      },
      "traits": ["dribbler", "fast"],
      "style": "inverted_winger",
      "contract": {
        "wage": 150000,
        "bonus": 40000,
        "contract_end": "2026-06-30",
        "release_clause": 1000000000,
        "years_left": 2
      },
      "market_value": 150000000,
      "form": "excellent",
      "morale": "happy",
      "fitness": 92,
      "injured": false,
      "suspended": false,
      "national_team_caps": 15,
      "national_team_goals": 5
    },
    {
      "id": "pedri",
      "name": "Педри",
      "name_en": "Pedri",
      "age": 21,
      "nationality": "spain",
      "position": "cm",
      "secondary_positions": ["am"],
      "foot": "right",
      "height": 174,
      "weight": 65,
      "rating": 87,
      "potential": 94,
      "stats": {
        "pace": 72,
        "shooting": 75,
        "passing": 88,
        "dribbling": 90,
        "defending": 68,
        "physical": 58,
        "finishing": 70,
        "heading": 45,
        "long_shots": 78,
        "composure": 90,
        "positioning": 85,
        "stamina": 80,
        "strength": 52,
        "jumping": 45,
        "agility": 90
      },
      "hidden_stats": {
        "injury_proneness": 45,
        "big_match_performance": 88,
        "consistency": 88,
        "adaptability": 82,
        "ambition": 90,
        "loyalty": 88,
        "pressure": 88,
        "professionalism": 90
      },
      "traits": ["playmaker", "dribbler"],
      "style": "advanced_playmaker",
      "contract": {
        "wage": 200000,
        "bonus": 50000,
        "contract_end": "2029-06-30",
        "release_clause": 1000000000,
        "years_left": 5
      },
      "market_value": 120000000,
      "form": "good",
      "morale": "happy",
      "fitness": 85,
      "injured": false,
      "suspended": false,
      "national_team_caps": 25,
      "national_team_goals": 4
    },
    {
      "id": "gavi",
      "name": "Гави",
      "name_en": "Gavi",
      "age": 19,
      "nationality": "spain",
      "position": "cm",
      "secondary_positions": ["am", "lm"],
      "foot": "right",
      "height": 173,
      "weight": 66,
      "rating": 84,
      "potential": 93,
      "stats": {
        "pace": 75,
        "shooting": 72,
        "passing": 82,
        "dribbling": 85,
        "defending": 72,
        "physical": 62,
        "finishing": 68,
        "heading": 48,
        "long_shots": 72,
        "composure": 82,
        "positioning": 80,
        "stamina": 85,
        "strength": 58,
        "jumping": 48,
        "agility": 88
      },
      "hidden_stats": {
        "injury_proneness": 40,
        "big_match_performance": 85,
        "consistency": 82,
        "adaptability": 78,
        "ambition": 90,
        "loyalty": 88,
        "pressure": 85,
        "professionalism": 88
      },
      "traits": ["ball_winner", "playmaker"],
      "style": "box_to_box",
      "contract": {
        "wage": 120000,
        "bonus": 30000,
        "contract_end": "2026-06-30",
        "release_clause": 1000000000,
        "years_left": 2
      },
      "market_value": 90000000,
      "form": "good",
      "morale": "happy",
      "fitness": 85,
      "injured": false,
      "suspended": false,
      "national_team_caps": 20,
      "national_team_goals": 3
    },
    {
      "id": "lewandowski",
      "name": "Роберт Левандовски",
      "name_en": "Robert Lewandowski",
      "age": 35,
      "nationality": "poland",
      "position": "st",
      "secondary_positions": [],
      "foot": "right",
      "height": 185,
      "weight": 81,
      "rating": 87,
      "potential": 87,
      "stats": {
        "pace": 68,
        "shooting": 90,
        "passing": 78,
        "dribbling": 80,
        "defending": 35,
        "physical": 75,
        "finishing": 92,
        "heading": 85,
        "long_shots": 82,
        "composure": 92,
        "positioning": 95,
        "stamina": 75,
        "strength": 78,
        "jumping": 80,
        "agility": 72
      },
      "hidden_stats": {
        "injury_proneness": 30,
        "big_match_performance": 90,
        "consistency": 92,
        "adaptability": 85,
        "ambition": 85,
        "loyalty": 88,
        "pressure": 92,
        "professionalism": 95
      },
      "traits": ["clinical_finisher", "aerial_threat"],
      "style": "complete_striker",
      "contract": {
        "wage": 250000,
        "bonus": 60000,
        "contract_end": "2025-06-30",
        "release_clause": 0,
        "years_left": 1
      },
      "market_value": 30000000,
      "form": "good",
      "morale": "happy",
      "fitness": 85,
      "injured": false,
      "suspended": false,
      "national_team_caps": 150,
      "national_team_goals": 82
    },
    {
      "id": "ter_stegen",
      "name": "Марк-Андре тер Штеген",
      "name_en": "Marc-André ter Stegen",
      "age": 32,
      "nationality": "germany",
      "position": "gk",
      "secondary_positions": [],
      "foot": "right",
      "height": 187,
      "weight": 85,
      "rating": 87,
      "potential": 87,
      "stats": {
        "pace": 32,
        "shooting": 18,
        "passing": 82,
        "dribbling": 42,
        "defending": 28,
        "physical": 75,
        "reflexes": 88,
        "handling": 85,
        "kicking": 85,
        "positioning": 88,
        "one_on_saves": 88,
        "aerial_ability": 82
      },
      "hidden_stats": {
        "injury_proneness": 35,
        "big_match_performance": 88,
        "consistency": 88,
        "adaptability": 85,
        "ambition": 85,
        "loyalty": 88,
        "pressure": 88,
        "professionalism": 92
      },
      "traits": ["sweeper"],
      "style": "sweeper_keeper",
      "contract": {
        "wage": 200000,
        "bonus": 50000,
        "contract_end": "2025-06-30",
        "release_clause": 100000000,
        "years_left": 1
      },
      "market_value": 40000000,
      "form": "good",
      "morale": "happy",
      "fitness": 85,
      "injured": false,
      "suspended": false,
      "national_team_caps": 85,
      "national_team_goals": 0
    },
    {
      "id": "araujo",
      "name": "Рональд Араухо",
      "name_en": "Ronald Araújo",
      "age": 25,
      "nationality": "uruguay",
      "position": "cb",
      "secondary_positions": ["rb"],
      "foot": "right",
      "height": 188,
      "weight": 84,
      "rating": 86,
      "potential": 90,
      "stats": {
        "pace": 78,
        "shooting": 42,
        "passing": 72,
        "dribbling": 68,
        "defending": 88,
        "physical": 85,
        "finishing": 32,
        "heading": 85,
        "long_shots": 42,
        "composure": 82,
        "positioning": 85,
        "stamina": 80,
        "strength": 85,
        "jumping": 88,
        "agility": 72
      },
      "hidden_stats": {
        "injury_proneness": 35,
        "big_match_performance": 85,
        "consistency": 82,
        "adaptability": 78,
        "ambition": 85,
        "loyalty": 82,
        "pressure": 85,
        "professionalism": 85
      },
      "traits": ["tough_tackler", "aerial_threat"],
      "style": "stopper",
      "contract": {
        "wage": 150000,
        "bonus": 35000,
        "contract_end": "2026-06-30",
        "release_clause": 1000000000,
        "years_left": 2
      },
      "market_value": 70000000,
      "form": "good",
      "morale": "happy",
      "fitness": 85,
      "injured": false,
      "suspended": false,
      "national_team_caps": 25,
      "national_team_goals": 2
    }
  ]
}